py_schedulerx/__init__.py
py_schedulerx/interval.py
py_schedulerx/job.py
py_schedulerx/scheduler.py
py_schedulerx/utils.py
py_schedulerx-0.1.0.dist-info/licenses/LICENSE
py_schedulerx-0.1.0.dist-info/METADATA
py_schedulerx-0.1.0.dist-info/WHEEL
py_schedulerx-0.1.0.dist-info/top_level.txt
py_schedulerx-0.1.0.dist-info/RECORD
