Metadata-Version: 2.4
Name: py-schedulerx
Version: 0.1.0
Summary: A lightweight and simple task scheduler for Python
Home-page: https://github.com/firatmio/py-schedulerx
Author: firatmio
Author-email: 
License: MIT
Project-URL: Homepage, https://github.com/firatmio/py-schedulerx
Project-URL: Repository, https://github.com/firatmio/py-schedulerx
Project-URL: Issues, https://github.com/firatmio/py-schedulerx/issues
Project-URL: Documentation, https://github.com/firatmio/py-schedulerx#readme
Keywords: scheduler,cron,task,job,automation,periodic,threading
Classifier: Development Status :: 4 - Beta
Classifier: Intended Audience :: Developers
Classifier: License :: OSI Approved :: MIT License
Classifier: Operating System :: OS Independent
Classifier: Programming Language :: Python :: 3
Classifier: Programming Language :: Python :: 3.8
Classifier: Programming Language :: Python :: 3.9
Classifier: Programming Language :: Python :: 3.10
Classifier: Programming Language :: Python :: 3.11
Classifier: Programming Language :: Python :: 3.12
Classifier: Topic :: Software Development :: Libraries :: Python Modules
Classifier: Topic :: System :: Monitoring
Classifier: Topic :: Utilities
Requires-Python: >=3.8
License-File: LICENSE
Dynamic: home-page
Dynamic: license-file
Dynamic: requires-python
